omicidx_sra/__init__.py
omicidx_sra/sra/__init__.py
omicidx_sra/sra/ebiutils.py
omicidx_sra/sra/parser.py
omicidx_sra/sra/pydantic_models.py
omicidx_sra-0.1.0.dist-info/WHEEL
omicidx_sra-0.1.0.dist-info/METADATA
omicidx_sra-0.1.0.dist-info/RECORD
