Metadata-Version: 2.1
Name: omicidx-sra
Version: 0.1.0
Summary: 
License: MIT
Author: Sean Davis
Author-email: seandavi@gmail.com
Requires-Python: >=3.8,<4.0
Classifier: License :: OSI Approved :: MIT License
Classifier: Programming Language :: Python :: 3
Classifier: Programming Language :: Python :: 3.8
Classifier: Programming Language :: Python :: 3.9
Requires-Dist: pydantic (>=1.9.0,<2.0.0)
Requires-Dist: requests (>=2.27.1,<3.0.0)
Requires-Dist: ujson (>=5.1.0,<6.0.0)
